apimoex/__init__.py
apimoex/client.py
apimoex/requests.py
apimoex-1.3.0.dist-info/LICENSE
apimoex-1.3.0.dist-info/METADATA
apimoex-1.3.0.dist-info/WHEEL
apimoex-1.3.0.dist-info/top_level.txt
apimoex-1.3.0.dist-info/RECORD
