Metadata-Version: 2.1
Name: apimoex
Version: 1.3.0
Summary: MOEX ISS API
Home-page: https://wlm1ke.github.io/apimoex/
Author: Mikhail Korotkov aka WLMike
Author-email: wlmike@gmail.com
License: http://unlicense.org
Project-URL: Source, https://github.com/WLM1ke/apimoex
Keywords: moex iss api
Platform: UNKNOWN
Classifier: Development Status :: 5 - Production/Stable
Classifier: Environment :: Other Environment
Classifier: Intended Audience :: Developers
Classifier: License :: Public Domain
Classifier: Natural Language :: Russian
Classifier: Operating System :: OS Independent
Classifier: Programming Language :: Python
Classifier: Programming Language :: Python :: 3
Classifier: Programming Language :: Python :: 3.6
Classifier: Programming Language :: Python :: 3.7
Classifier: Programming Language :: Python :: Implementation :: CPython
Classifier: Topic :: Utilities
Requires-Python: >=3.6
License-File: LICENSE
Requires-Dist: requests
